{"id":"78jz34sn4cc8vqpsn87h7lp","title":"Projet Systèmes Hybrides","desc":"","updated":1673515698137,"created":1672905859927,"custom":{},"fname":"Projet.PSH","type":"note","vault":{"fsPath":"vault"},"contentHash":"7e62088797718b286d11ed0df332073a","links":[{"type":"wiki","from":{"fname":"Projet.PSH","id":"78jz34sn4cc8vqpsn87h7lp","vaultName":"vault"},"value":"Projet.PSH.Presentation","alias":"Présentation des Systèmes Hybrides","position":{"start":{"line":11,"column":3,"offset":275},"end":{"line":11,"column":65,"offset":337},"indent":[]},"xvault":false,"sameFile":false,"to":{"fname":"Projet.PSH.Presentation"}},{"type":"wiki","from":{"fname":"Projet.PSH","id":"78jz34sn4cc8vqpsn87h7lp","vaultName":"vault"},"value":"Projet.PSH.Modelisation","alias":"Modélisation des Systèmes Hybrides","position":{"start":{"line":12,"column":3,"offset":340},"end":{"line":12,"column":65,"offset":402},"indent":[]},"xvault":false,"sameFile":false,"to":{"fname":"Projet.PSH.Modelisation"}},{"type":"wiki","from":{"fname":"Projet.PSH","id":"78jz34sn4cc8vqpsn87h7lp","vaultName":"vault"},"value":"Projet.PSH.Trajectoires","alias":"Trajectoires des Systèmes Hybrides","position":{"start":{"line":13,"column":3,"offset":405},"end":{"line":13,"column":65,"offset":467},"indent":[]},"xvault":false,"sameFile":false,"to":{"fname":"Projet.PSH.Trajectoires"}},{"type":"wiki","from":{"fname":"Projet.PSH","id":"78jz34sn4cc8vqpsn87h7lp","vaultName":"vault"},"value":"Projet.PSH.Proprietes","alias":"Proprietes des Systèmes Hybrides","position":{"start":{"line":14,"column":3,"offset":470},"end":{"line":14,"column":61,"offset":528},"indent":[]},"xvault":false,"sameFile":false,"to":{"fname":"Projet.PSH.Proprietes"}},{"from":{"fname":"Projet","id":"g54kxj2u0t1wl4x6uo6vgbt","vaultName":"vault"},"type":"backlink","position":{"start":{"line":3,"column":3,"offset":20},"end":{"line":3,"column":17,"offset":34},"indent":[]},"value":"Projet.PSH"}],"anchors":{"cours":{"type":"header","text":"Cours","value":"cours","line":15,"column":0,"depth":1},"bibliographie":{"type":"header","text":"Bibliographie","value":"bibliographie","line":22,"column":0,"depth":1}},"children":["5luve6pwb9nnko5oy12y0li","wdg7ze3g69ljyz23kg87zgz","cqjgwfxcbasqos9go5kdaor","zyoxdqomtout3k28znspy96"],"parent":"g54kxj2u0t1wl4x6uo6vgbt","data":{}}
