{"id":"qlxx1xvgg5f4r1qmipmr74v","title":"CNN - Convolutional Neural Networks","desc":"","updated":1675621347298,"created":1675062032325,"custom":{},"fname":"B3.AA.CM.CNN","type":"note","vault":{"fsPath":"vault"},"contentHash":"ece406ed705e8cc418ccf2f511211b42","links":[{"from":{"fname":"B3.AA","id":"wyd35u3oxvhvedd1pwhct4j","vaultName":"vault"},"type":"backlink","position":{"start":{"line":23,"column":3,"offset":468},"end":{"line":23,"column":19,"offset":484},"indent":[]},"value":"B3.AA.CM.CNN"},{"from":{"fname":"B3.AA.TD2.Convolution","id":"snuwegzdfkojmt8uzvtrvt8","vaultName":"vault"},"type":"backlink","position":{"start":{"line":62,"column":26,"offset":2574},"end":{"line":62,"column":65,"offset":2613},"indent":[]},"value":"B3.AA.CM.CNN"},{"from":{"fname":"B3.AA.TD2.Convolution","id":"snuwegzdfkojmt8uzvtrvt8","vaultName":"vault"},"type":"backlink","position":{"start":{"line":73,"column":31,"offset":3234},"end":{"line":73,"column":74,"offset":3277},"indent":[]},"value":"B3.AA.CM.CNN"}],"anchors":{"problématique":{"type":"header","text":"Problématique","value":"problématique","line":23,"column":0,"depth":1},"quest-ce-quune-image-pour-lordinateur-":{"type":"header","text":"Qu'est-ce qu'une image pour l'ordinateur ?","value":"quest-ce-quune-image-pour-lordinateur-","line":25,"column":0,"depth":2},"exemple-de-tâche-en-computer-vision":{"type":"header","text":"Exemple de tâche en Computer Vision","value":"exemple-de-tâche-en-computer-vision","line":32,"column":0,"depth":2},"premières-approches-possibles":{"type":"header","text":"Premières approches possibles","value":"premières-approches-possibles","line":39,"column":0,"depth":2},"approche-connectée":{"type":"header","text":"Approche connectée","value":"approche-connectée","line":46,"column":0,"depth":3},"approche-hiérarchiqueconvolutive":{"type":"header","text":"Approche hiérarchique/convolutive","value":"approche-hiérarchiqueconvolutive","line":51,"column":0,"depth":3},"sommaire":{"type":"header","text":"Sommaire","value":"sommaire","line":57,"column":0,"depth":1},"i--introduction":{"type":"header","text":"I- Introduction","value":"i--introduction","line":61,"column":0,"depth":1},"suivre-iss":{"type":"header","text":"Suivre ISS","value":"suivre-iss","line":63,"column":0,"depth":2},"terminologie":{"type":"header","text":"Terminologie","value":"terminologie","line":68,"column":0,"depth":2},"implémentation":{"type":"header","text":"Implémentation","value":"implémentation","line":79,"column":0,"depth":2},"propriétés":{"type":"header","text":"Propriétés","value":"propriétés","line":86,"column":0,"depth":2},"illustration":{"type":"header","text":"Illustration","value":"illustration","line":94,"column":0,"depth":2},"ex-détection-de-bords-verticaux":{"type":"header","text":"Ex: Détection de bords verticaux","value":"ex-détection-de-bords-verticaux","line":105,"column":0,"depth":2},"bords-verticaux":{"type":"header","text":"Bords Verticaux","value":"bords-verticaux","line":107,"column":0,"depth":3},"bords-horizentaux":{"type":"header","text":"Bords Horizentaux","value":"bords-horizentaux","line":112,"column":0,"depth":3},"bords-complexes":{"type":"header","text":"Bords Complexes","value":"bords-complexes","line":116,"column":0,"depth":3},"apprentissage":{"type":"header","text":"Apprentissage","value":"apprentissage","line":121,"column":0,"depth":2},"exemple":{"type":"header","text":"Exemple","value":"exemple","line":125,"column":0,"depth":3},"couche-de-convolution":{"type":"header","text":"Couche de convolution","value":"couche-de-convolution","line":129,"column":0,"depth":2},"multicanal":{"type":"header","text":"Multicanal","value":"multicanal","line":138,"column":0,"depth":2},"conv2d-en-pytorch":{"type":"header","text":"Conv2d en Pytorch","value":"conv2d-en-pytorch","line":149,"column":0,"depth":2},"convolition-vizualizer":{"type":"header","text":"Convolition Vizualizer","value":"convolition-vizualizer","line":202,"column":0,"depth":2},"implémentation-sous-jacente-de-pytorch":{"type":"header","text":"Implémentation sous-jacente de PyTorch","value":"implémentation-sous-jacente-de-pytorch","line":223,"column":0,"depth":2},"gemm---general-matrix-multiplication":{"type":"header","text":"GEMM - General Matrix Multiplication","value":"gemm---general-matrix-multiplication","line":225,"column":0,"depth":3},"im2col":{"type":"header","text":"Im2Col","value":"im2col","line":231,"column":0,"depth":3},"forward":{"type":"header","text":"Forward","value":"forward","line":235,"column":0,"depth":3},"backward":{"type":"header","text":"Backward","value":"backward","line":241,"column":0,"depth":3},"winograd":{"type":"header","text":"Winograd","value":"winograd","line":248,"column":0,"depth":3},"bilan":{"type":"header","text":"Bilan","value":"bilan","line":254,"column":0,"depth":2},"max-pooling":{"type":"header","text":"Max-Pooling","value":"max-pooling","line":258,"column":0,"depth":2},"champ-réceptif-receptive-field":{"type":"header","text":"Champ réceptif (Receptive Field)","value":"champ-réceptif-receptive-field","line":264,"column":0,"depth":2},"réseau-lenet":{"type":"header","text":"Réseau LeNet","value":"réseau-lenet","line":268,"column":0,"depth":2},"réseau-alexnet":{"type":"header","text":"Réseau AlexNet","value":"réseau-alexnet","line":272,"column":0,"depth":2},"réseau-vggnet":{"type":"header","text":"Réseau VGGNet","value":"réseau-vggnet","line":276,"column":0,"depth":2},"démo-en-ligne":{"type":"header","text":"Démo en ligne","value":"démo-en-ligne","line":280,"column":0,"depth":2},"couche-de-batch-normalisation":{"type":"header","text":"Couche de Batch-normalisation","value":"couche-de-batch-normalisation","line":285,"column":0,"depth":2},"autres-couches-de-normalisation":{"type":"header","text":"Autres couches de normalisation","value":"autres-couches-de-normalisation","line":290,"column":0,"depth":2},"fcn---fully-convolutional-network":{"type":"header","text":"FCN - Fully convolutional Network","value":"fcn---fully-convolutional-network","line":294,"column":0,"depth":2},"residual-networks-resnet":{"type":"header","text":"Residual Networks (ResNet)","value":"residual-networks-resnet","line":298,"column":0,"depth":2},"autres-types-de-convolution":{"type":"header","text":"Autres types de convolution","value":"autres-types-de-convolution","line":309,"column":0,"depth":2},"larchitecture-xception":{"type":"header","text":"L'architecture Xception","value":"larchitecture-xception","line":320,"column":0,"depth":2},"larchitecture-convmixer":{"type":"header","text":"L'architecture Convmixer","value":"larchitecture-convmixer","line":324,"column":0,"depth":2},"la-convolution-dilatée":{"type":"header","text":"La convolution dilatée","value":"la-convolution-dilatée","line":328,"column":0,"depth":2},"la-convolution-sur-un-signal-sonore":{"type":"header","text":"La convolution sur un signal sonore","value":"la-convolution-sur-un-signal-sonore","line":332,"column":0,"depth":2},"la-convolution-sur-des-données-textuelles":{"type":"header","text":"La convolution sur des données textuelles","value":"la-convolution-sur-des-données-textuelles","line":336,"column":0,"depth":2},"plongements-de-mots-word-embeddings":{"type":"header","text":"Plongements de mots (word embeddings)","value":"plongements-de-mots-word-embeddings","line":340,"column":0,"depth":3},"remarques":{"type":"header","text":"Remarques","value":"remarques","line":345,"column":0,"depth":3},"vers-linterpratibilité-des-cnn":{"type":"header","text":"Vers l'interpratibilité des CNN","value":"vers-linterpratibilité-des-cnn","line":350,"column":0,"depth":2},"résumé-cnn":{"type":"header","text":"Résumé CNN","value":"résumé-cnn","line":371,"column":0,"depth":2}},"children":[],"parent":"mq4u4tyxrc20unmxo58mfov","data":{}}
